sensor_analysis/__init__.py
sensor_analysis/data_aggregation.py
sensor_analysis/data_loading.py
sensor_analysis/data_merging.py
sensor_analysis/data_metrics.py
sensor_analysis/data_plotting.py
sensor_analysis/data_statistics.py
sensor_analysis-0.1.dist-info/LICENSE
sensor_analysis-0.1.dist-info/METADATA
sensor_analysis-0.1.dist-info/WHEEL
sensor_analysis-0.1.dist-info/top_level.txt
sensor_analysis-0.1.dist-info/RECORD
